barriers/__init__.py
barriers/barriers.py
barriers-2.0.0.dist-info/licenses/LICENSE
barriers-2.0.0.dist-info/METADATA
barriers-2.0.0.dist-info/WHEEL
barriers-2.0.0.dist-info/top_level.txt
barriers-2.0.0.dist-info/RECORD
